<?xml version="1.0" encoding="utf-8"?>
<annotation>
   <filename>fashion_0498</filename>
   <category>fashion</category>
   <size>
      <width>225</width>
      <height>300</height>
   </size>
   <layout>
      <element label="image" polygon_x="1 1 225 225 1 1" polygon_y="2 300 300 1 1 2"/>
      <element label="text-over-image" polygon_x="31 31 135 135 31 31"
               polygon_y="287 295 295 286 286 287"/>
      <element label="text-over-image" polygon_x="36 36 130 130 36 36"
               polygon_y="267 275 275 266 266 267"/>
      <element label="headline-over-image" polygon_x="26 26 130 130 26 26"
               polygon_y="182 245 245 181 181 182"/>
   </layout>
   <text>
      <keyword>fragrance</keyword>
   </text>
</annotation>