<?xml version="1.0" encoding="utf-8"?>
<annotation>
   <filename>news_0071</filename>
   <category>news</category>
   <size>
      <width>225</width>
      <height>300</height>
   </size>
   <layout>
      <element label="text" polygon_x="11 11 135 135 60 60 61 61 135 135 11 11"
               polygon_y="112 280 280 211 211 210 146 145 145 111 111 112"/>
      <element label="text" polygon_x="151 151 176 176 175 175 151 151 215 215 151 151"
               polygon_y="22 145 145 146 210 211 211 280 280 21 21 22"/>
      <element label="text" polygon_x="11 11 135 135 11 11" polygon_y="22 95 95 21 21 22"/>
      <element label="text" polygon_x="71 71 165 165 71 71"
               polygon_y="157 190 190 156 156 157"/>
      <element label="text" polygon_x="46 46 100 100 46 46"
               polygon_y="102 105 105 101 101 102"/>
   </layout>
   <text>
      <keyword>fight</keyword>
      <keyword>fact</keyword>
      <keyword>grow</keyword>
      <keyword>nation</keyword>
   </text>
</annotation>