<?xml version="1.0" encoding="utf-8"?>
<annotation>
   <filename>news_0411</filename>
   <category>news</category>
   <size>
      <width>225</width>
      <height>300</height>
   </size>
   <layout>
      <element label="text" polygon_x="146 146 210 210 146 146"
               polygon_y="57 145 145 56 56 57"/>
      <element label="text" polygon_x="81 81 140 140 81 81"
               polygon_y="192 255 255 191 191 192"/>
      <element label="text" polygon_x="146 146 210 210 146 146"
               polygon_y="152 210 210 151 151 152"/>
      <element label="text" polygon_x="16 16 75 75 16 16" polygon_y="202 250 250 201 201 202"/>
      <element label="text" polygon_x="146 146 210 210 146 146"
               polygon_y="257 295 295 256 256 257"/>
      <element label="text" polygon_x="146 146 210 210 146 146" polygon_y="17 50 50 16 16 17"/>
      <element label="text" polygon_x="146 146 210 210 146 146"
               polygon_y="217 250 250 216 216 217"/>
      <element label="text" polygon_x="16 16 75 75 16 16" polygon_y="257 290 290 256 256 257"/>
      <element label="text" polygon_x="81 81 140 140 81 81"
               polygon_y="262 290 290 261 261 262"/>
      <element label="text" polygon_x="16 16 75 75 16 16" polygon_y="182 195 195 181 181 182"/>
      <element label="text" polygon_x="81 81 140 140 81 81"
               polygon_y="182 185 185 181 181 182"/>
      <element label="text" polygon_x="61 61 100 100 61 61" polygon_y="17 20 20 16 16 17"/>
      <element label="text" polygon_x="61 61 100 100 61 61" polygon_y="42 45 45 41 41 42"/>
      <element label="image" polygon_x="21 21 140 140 21 21" polygon_y="52 175 175 51 51 52"/>
      <element label="headline" polygon_x="41 41 120 120 41 41" polygon_y="27 35 35 26 26 27"/>
   </layout>
   <text>
      <keyword>power</keyword>
      <keyword>money</keyword>
      <keyword>cost</keyword>
      <keyword>question</keyword>
   </text>
</annotation>