<?xml version="1.0" encoding="utf-8"?>
<annotation>
   <filename>travel_0557</filename>
   <category>travel</category>
   <size>
      <width>225</width>
      <height>300</height>
   </size>
   <layout>
      <element label="image" polygon_x="6 6 225 225 6 6" polygon_y="7 295 295 6 6 7"/>
      <element label="text-over-image" polygon_x="66 66 195 195 66 66"
               polygon_y="47 105 105 46 46 47"/>
      <element label="headline-over-image" polygon_x="26 26 210 210 26 26"
               polygon_y="12 25 25 11 11 12"/>
   </layout>
   <text>
      <keyword>island</keyword>
      <keyword>join</keyword>
      <keyword>picture</keyword>
      <keyword>visitor</keyword>
      <keyword>north</keyword>
   </text>
</annotation>