<?xml version="1.0" encoding="utf-8"?>
<annotation>
   <filename>travel_0492</filename>
   <category>travel</category>
   <size>
      <width>225</width>
      <height>300</height>
   </size>
   <layout>
      <element label="text" polygon_x="136 136 210 210 136 136"
               polygon_y="122 280 280 121 121 122"/>
      <element label="text" polygon_x="6 6 75 75 6 6" polygon_y="62 85 85 61 61 62"/>
      <element label="text" polygon_x="136 136 210 210 136 136"
               polygon_y="97 115 115 96 96 97"/>
      <element label="text" polygon_x="36 36 75 75 36 36" polygon_y="12 45 45 11 11 12"/>
      <element label="image" polygon_x="1 1 130 130 1 1" polygon_y="92 280 280 91 91 92"/>
      <element label="image" polygon_x="81 81 210 210 81 81" polygon_y="2 85 85 1 1 2"/>
      <element label="image" polygon_x="1 1 30 30 1 1" polygon_y="12 45 45 11 11 12"/>
   </layout>
   <text>
      <keyword>place</keyword>
      <keyword>love</keyword>
      <keyword>house</keyword>
      <keyword>top</keyword>
      <keyword>beach</keyword>
      <keyword>tree</keyword>
      <keyword>child</keyword>
      <keyword>restaurant</keyword>
      <keyword>kitchen</keyword>
      <keyword>inspire</keyword>
      <keyword>island</keyword>
      <keyword>shop</keyword>
   </text>
</annotation>