<?xml version="1.0" encoding="utf-8"?>
<annotation>
   <filename>travel_0342</filename>
   <category>travel</category>
   <size>
      <width>225</width>
      <height>300</height>
   </size>
   <layout>
      <element label="text" polygon_x="41 41 110 110 41 41"
               polygon_y="232 285 285 231 231 232"/>
      <element label="text" polygon_x="116 116 180 180 116 116"
               polygon_y="232 285 285 231 231 232"/>
      <element label="text" polygon_x="41 41 180 180 41 41"
               polygon_y="192 205 205 191 191 192"/>
      <element label="image" polygon_x="6 6 220 220 6 6" polygon_y="2 150 150 1 1 2"/>
      <element label="headline" polygon_x="31 31 190 190 31 31"
               polygon_y="177 185 185 176 176 177"/>
   </layout>
   <text>
      <keyword>place</keyword>
      <keyword>visit</keyword>
      <keyword>room</keyword>
      <keyword>food</keyword>
      <keyword>restaurant</keyword>
      <keyword>inspire</keyword>
      <keyword>story</keyword>
      <keyword>hill</keyword>
      <keyword>valley</keyword>
      <keyword>sheep</keyword>
   </text>
</annotation>