<?xml version="1.0" encoding="utf-8"?>
<annotation>
   <filename>travel_0290</filename>
   <category>travel</category>
   <size>
      <width>225</width>
      <height>300</height>
   </size>
   <layout>
      <element label="text" polygon_x="26 26 165 165 26 26"
               polygon_y="132 155 155 131 131 132"/>
      <element label="text" polygon_x="16 16 145 145 16 16"
               polygon_y="282 295 295 281 281 282"/>
      <element label="text" polygon_x="16 16 105 105 16 16"
               polygon_y="242 260 260 241 241 242"/>
      <element label="text" polygon_x="116 116 200 200 116 116"
               polygon_y="242 260 260 241 241 242"/>
      <element label="text" polygon_x="16 16 55 55 16 16" polygon_y="267 275 275 266 266 267"/>
      <element label="text" polygon_x="116 116 150 150 116 116"
               polygon_y="267 275 275 266 266 267"/>
      <element label="image" polygon_x="81 81 220 220 205 205 205 176 175 175 81 81"
               polygon_y="37 125 125 36 36 35 1 1 35 36 36 37"/>
      <element label="image" polygon_x="116 116 220 220 116 116"
               polygon_y="162 235 235 161 161 162"/>
      <element label="image" polygon_x="16 16 110 110 16 16"
               polygon_y="162 235 235 161 161 162"/>
      <element label="image" polygon_x="16 16 75 75 16 16" polygon_y="37 80 80 36 36 37"/>
      <element label="image" polygon_x="16 16 75 75 16 16" polygon_y="87 125 125 86 86 87"/>
      <element label="headline" polygon_x="31 31 160 160 31 31" polygon_y="22 30 30 21 21 22"/>
   </layout>
   <text>
      <keyword>garden</keyword>
   </text>
</annotation>