<?xml version="1.0" encoding="utf-8"?>
<annotation>
   <filename>wedding_0085</filename>
   <category>wedding</category>
   <size>
      <width>225</width>
      <height>300</height>
   </size>
   <layout>
      <element label="text" polygon_x="66 66 165 165 66 66"
               polygon_y="267 280 280 266 266 267"/>
      <element label="image" polygon_x="31 31 200 200 31 31" polygon_y="2 235 235 1 1 2"/>
      <element label="text-over-image" polygon_x="41 41 190 190 41 41"
               polygon_y="222 230 230 221 221 222"/>
   </layout>
   <text/>
</annotation>